[
  {
    "pluginName": "文字图标生成器",
    "usageCount": 2,
    "totalUsageDuration": 0.0,
    "lastUsed": [
      2025,
      3,
      10,
      18,
      36,
      32,
      647594000
    ]
  },
  {
    "pluginName": "JSON格式化",
    "usageCount": 2,
    "totalUsageDuration": 0.0,
    "lastUsed": [
      2025,
      3,
      10,
      18,
      36,
      32,
      639525000
    ]
  },
  {
    "pluginName": "Base64转换",
    "usageCount": 1,
    "totalUsageDuration": 0.0,
    "lastUsed": [
      2025,
      3,
      10,
      18,
      36,
      32,
      854713000
    ]
  },
  {
    "pluginName": "JSON转JavaBean",
    "usageCount": 1,
    "totalUsageDuration": 0.0,
    "lastUsed": [
      2025,
      3,
      10,
      18,
      36,
      33,
      102731000
    ]
  },
  {
    "pluginName": "Hosts编辑器",
    "usageCount": 1,
    "totalUsageDuration": 0.0,
    "lastUsed": [
      2025,
      3,
      10,
      18,
      36,
      33,
      100619000
    ]
  }
]